pdb2sql/StructureSimilarity.py
pdb2sql/__init__.py
pdb2sql/__version__.py
pdb2sql/align.py
pdb2sql/interface.py
pdb2sql/many2sql.py
pdb2sql/pdb2sql_base.py
pdb2sql/pdb2sqlcore.py
pdb2sql/superpose.py
pdb2sql/transform.py
pdb2sql/utils.py
test/__init__.py
test/test_align.py
test/test_interface.py
test/test_many2sql.py
test/test_pdb2sqlcore.py
test/test_structureSimilarity.py
test/test_superpose.py
test/test_transform.py
test/test_utils.py
test/utils.py
test/pdb/3CRO.pdb
test/pdb/3CRO_H.pdb
test/pdb/dummy_blank_chainID_with_segID.pdb
test/pdb/dummy_blank_chainID_without_segID.pdb
test/pdb/dummy_blank_element.pdb
test/pdb/dummy_blank_occupancy.pdb
test/pdb/dummy_blank_temperature.pdb
test/pdb/dummy_longline.pdb
test/pdb/dummy_template.pdb
test/pdb/dummy_transform.pdb
test/pdb/test_model.pdb
test/pdb/1AK4/1AK4_10w.pdb
test/pdb/1AK4/1AK4_10w_aligned.pdb
test/pdb/1AK4/1AK4_5w.pdb
test/pdb/1AK4/1AK4_5w_nonmatch.pdb
test/pdb/1AK4/target.izone
test/pdb/1AK4/target.lzone
test/pdb/1AK4/target.pdb
pdb2sql-0.5.3.dist-info/LICENSE
pdb2sql-0.5.3.dist-info/METADATA
pdb2sql-0.5.3.dist-info/NOTICE
pdb2sql-0.5.3.dist-info/WHEEL
pdb2sql-0.5.3.dist-info/top_level.txt
pdb2sql-0.5.3.dist-info/RECORD
