Metadata-Version: 2.1
Name: pdb2sql
Version: 0.5.3
Summary: PDB parser using SQL queries
Home-page: https://github.com/DeepRank/pdb2sql
Author: ['Nicolas Renaud']
Author-email: n.renaud@esciencecenter.nl
License: Apache Software License 2.0
Keywords: PDB2SQL
Classifier: Development Status :: 2 - Pre-Alpha
Classifier: Intended Audience :: Developers
Classifier: License :: OSI Approved :: Apache Software License
Classifier: Natural Language :: English
Classifier: Intended Audience :: Science/Research
Classifier: Programming Language :: Python :: 3.7
Classifier: Topic :: Scientific/Engineering :: Bio-Informatics
License-File: LICENSE
License-File: NOTICE
Requires-Dist: numpy
Requires-Dist: pandas
Provides-Extra: dev
Requires-Dist: prospector[with_pyroma] ; extra == 'dev'
Requires-Dist: autopep8 ; extra == 'dev'
Requires-Dist: isort ; extra == 'dev'
Requires-Dist: twine ; extra == 'dev'
Provides-Extra: docs
Requires-Dist: sphinx ; extra == 'docs'
Requires-Dist: ipython ; extra == 'docs'
Provides-Extra: test
Requires-Dist: coveralls ; extra == 'test'
Requires-Dist: pytest ; extra == 'test'
Requires-Dist: pytest-cov ; extra == 'test'
